gradient_mechanics/__init__.py
gradient_mechanics/benchmarking/__init__.py
gradient_mechanics/benchmarking/platform_info.py
gradient_mechanics/data/__init__.py
gradient_mechanics/data/episodes.py
gradient_mechanics/data/gpu_iterator.py
gradient_mechanics/data/torch_loading.py
gradient_mechanics/data/torchdata_loading.py
gradient_mechanics/data/transforms.py
gradient_mechanics/data/video_demuxing.py
gradient_mechanics/data/video_indexing.py
gradient_mechanics/data/video_transforms.py
gradient_mechanics-0.0.4.dist-info/METADATA
gradient_mechanics-0.0.4.dist-info/WHEEL
gradient_mechanics-0.0.4.dist-info/licenses/LICENSE
gradient_mechanics-0.0.4.dist-info/RECORD
