Metadata-Version: 2.4
Name: gradient-mechanics
Version: 0.0.4
Summary: Accelerated deep learning.
License-File: LICENSE
Requires-Python: >=3.10
Requires-Dist: cvcuda-cu12>=0.14.0
Requires-Dist: numpy>=1.26.0
Requires-Dist: nvidia-nvimgcodec-cu12>=0.5.0.13
Requires-Dist: pyav>=13.1.0
Requires-Dist: pynvvideocodec>=1.0.2
Requires-Dist: torch>=2.0.1
